setup.py
example_canopy_kmeans/__init__.py
example_canopy_kmeans/test.py
example_canopy_kmeans.egg-info/PKG-INFO
example_canopy_kmeans.egg-info/SOURCES.txt
example_canopy_kmeans.egg-info/dependency_links.txt
example_canopy_kmeans.egg-info/top_level.txt