Metadata-Version: 2.1
Name: example-canopy-kmeans
Version: 1.0.5
Summary: 聚类库
Home-page: https://github.com/
Author: YR
Author-email: 395622703@qq.com
License: UNKNOWN
Platform: UNKNOWN
Classifier: Programming Language :: Python :: 3
Classifier: License :: OSI Approved :: MIT License
Classifier: Operating System :: OS Independent
